banhammer/WELCOME.md
banhammer/__init__.py
banhammer/banhammer.py
banhammer/const.py
banhammer/reactions.yaml
banhammer/exceptions/__init__.py
banhammer/exceptions/exceptions.py
banhammer/models/__init__.py
banhammer/models/event_handler.py
banhammer/models/item.py
banhammer/models/message_builder.py
banhammer/models/reaction.py
banhammer/models/subreddit.py
banhammer/utils/__init__.py
banhammer/utils/reddit_helper.py
banhammer/utils/yaml.py
Banhammer.py-2.5.4b0.dist-info/LICENSE
Banhammer.py-2.5.4b0.dist-info/METADATA
Banhammer.py-2.5.4b0.dist-info/WHEEL
Banhammer.py-2.5.4b0.dist-info/top_level.txt
Banhammer.py-2.5.4b0.dist-info/RECORD
