Metadata-Version: 2.1
Name: Banhammer.py
Version: 2.5.4b0
Summary: A Discord bot integration framework for Reddit moderation.
Home-page: https://github.com/Dan6erbond/Banhammer.py
Author: Dan6erbond
Author-email: moravrav@gmail.com
License: GNU General Public License v3 (GPLv3)
Platform: UNKNOWN
Classifier: Development Status :: 4 - Beta
Classifier: Intended Audience :: Developers
Classifier: Natural Language :: English
Classifier: Programming Language :: Python :: 3.6
Classifier: Programming Language :: Python :: 3.7
Classifier: Operating System :: OS Independent
Classifier: Topic :: Communications
Classifier: Topic :: Internet
Classifier: Topic :: Utilities
Classifier: Topic :: Software Development :: Libraries
Classifier: Topic :: Software Development :: Libraries :: Application Frameworks
Classifier: Topic :: Software Development :: Libraries :: Python Modules
Classifier: License :: OSI Approved :: GNU General Public License v3 (GPLv3)
Classifier: Operating System :: OS Independent
Requires-Dist: discord.py (>=1.1.1)
Requires-Dist: apraw (>=0.6.6a0)
